{"doc":" 数据字典信息\n\n @author admin\n","fields":[],"enumConstants":[],"methods":[{"name":"list","paramTypes":["java.lang.String","java.lang.String"],"doc":" 查询字典类型列表\n @param xyDictTypeJson\n @param pageQueryJson\n @return\n"},{"name":"getInfo","paramTypes":["java.lang.Long"],"doc":" 查询字典类型详细\n\n @param dictId 字典ID\n"},{"name":"add","paramTypes":["com.yixin.xiaoyi.system.entity.XyDictType"],"doc":" 新增字典类型\n @param dict\n @return\n"},{"name":"edit","paramTypes":["com.yixin.xiaoyi.system.entity.XyDictType"],"doc":" 修改字典类型\n @param dict\n @return\n"},{"name":"remove","paramTypes":["java.lang.Long[]"],"doc":" 删除字典类型\n\n @param dictIds 字典ID串\n"},{"name":"refreshCache","paramTypes":[],"doc":" 刷新字典缓存\n @return\n"},{"name":"optionselect","paramTypes":[],"doc":" 获取字典选择框列表\n @return\n"}],"constructors":[]}